CHANGES.rst
MANIFEST.in
README.rst
buildout.cfg
setup.cfg
setup.py
travis.cfg
docs/LICENSE.GPL
docs/LICENSE.rst
src/collective/__init__.py
src/collective.js.tooltipster.egg-info/PKG-INFO
src/collective.js.tooltipster.egg-info/SOURCES.txt
src/collective.js.tooltipster.egg-info/dependency_links.txt
src/collective.js.tooltipster.egg-info/entry_points.txt
src/collective.js.tooltipster.egg-info/namespace_packages.txt
src/collective.js.tooltipster.egg-info/not-zip-safe
src/collective.js.tooltipster.egg-info/requires.txt
src/collective.js.tooltipster.egg-info/top_level.txt
src/collective/js/__init__.py
src/collective/js/tooltipster/__init__.py
src/collective/js/tooltipster/configure.zcml
src/collective/js/tooltipster/interfaces.py
src/collective/js/tooltipster/setuphandlers.py
src/collective/js/tooltipster/testing.py
src/collective/js/tooltipster/testing.zcml
src/collective/js/tooltipster/upgrades.py
src/collective/js/tooltipster/browser/__init__.py
src/collective/js/tooltipster/browser/configure.zcml
src/collective/js/tooltipster/browser/overrides/.gitkeep
src/collective/js/tooltipster/browser/static/.gitkeep
src/collective/js/tooltipster/browser/static/tooltipster-sideTip-borderless.min.css
src/collective/js/tooltipster/browser/static/tooltipster-sideTip-light.min.css
src/collective/js/tooltipster/browser/static/tooltipster-sideTip-noir.min.css
src/collective/js/tooltipster/browser/static/tooltipster-sideTip-punk.min.css
src/collective/js/tooltipster/browser/static/tooltipster-sideTip-shadow.min.css
src/collective/js/tooltipster/browser/static/tooltipster.bundle.min.css
src/collective/js/tooltipster/browser/static/tooltipster.bundle.min.js
src/collective/js/tooltipster/browser/static/tooltipster_helper.js
src/collective/js/tooltipster/profiles/default/browserlayer.xml
src/collective/js/tooltipster/profiles/default/collectivejstooltipster_marker.txt
src/collective/js/tooltipster/profiles/default/cssregistry.xml
src/collective/js/tooltipster/profiles/default/jsregistry.xml
src/collective/js/tooltipster/profiles/default/metadata.xml
src/collective/js/tooltipster/profiles/testing/collectivejsiframeresizer_testing.txt
src/collective/js/tooltipster/profiles/testing/metadata.xml
src/collective/js/tooltipster/profiles/themes/cssregistry.xml
src/collective/js/tooltipster/tests/__init__.py
src/collective/js/tooltipster/tests/test_robot.py
src/collective/js/tooltipster/tests/test_setup.py
