Metadata-Version: 2.1
Name: collective.js.tooltipster
Version: 1.8
Summary: Plone integration of tooltipster jquery plugin
Home-page: http://pypi.python.org/pypi/collective.js.tooltipster
Author: Gauthier BASTIEN
Author-email: gauthier.bastien@imio.be
License: GPL
Keywords: Python Plone
Platform: UNKNOWN
Classifier: Development Status :: 6 - Mature
Classifier: Environment :: Web Environment
Classifier: Framework :: Plone
Classifier: Framework :: Plone :: 4.3
Classifier: License :: OSI Approved :: GNU General Public License (GPL)
Classifier: Programming Language :: Python
Classifier: Programming Language :: Python :: 2.7
Provides-Extra: test
